django_telethon_session/__init__.py
django_telethon_session/admin.py
django_telethon_session/apps.py
django_telethon_session/models.py
django_telethon_session/sessions.py
django_telethon_session/migrations/0001_initial.py
django_telethon_session/migrations/__init__.py
django_telethon_session-0.9.dist-info/LICENSE
django_telethon_session-0.9.dist-info/METADATA
django_telethon_session-0.9.dist-info/WHEEL
django_telethon_session-0.9.dist-info/top_level.txt
django_telethon_session-0.9.dist-info/RECORD
